authit/__init__.py
authit/admin.py
authit/middleware/__init__.py
authit/middleware/jwt.py
authit/middleware/logging.py
authit/migrations/0001_initial.py
authit/migrations/0002_group.py
authit/migrations/0003_alter_user_modified.py
authit/migrations/0004_alter_user_last_activity.py
authit/migrations/0005_remove_group_permissions_groupmember.py
authit/migrations/0006_group_uuid.py
authit/migrations/0007_user_date_joined_user_first_name_user_is_staff_and_more.py
authit/migrations/__init__.py
authit/models/__init__.py
authit/models/ad
authit/models/group.py
authit/models/member.py
authit/models/user.py
authit/rest/__init__.py
authit/rest/group.py
authit/rest/user.py
authit/utils/__init__.py
authit/utils/jwtoken.py
jestit/__init__.py
jestit/admin.py
jestit/decorators/__init__.py
jestit/decorators/auth.py
jestit/decorators/cron.py
jestit/decorators/http.py
jestit/decorators/validate.py
jestit/errors.py
jestit/helpers/__init__.py
jestit/helpers/cron.py
jestit/helpers/crypto.py
jestit/helpers/daemon.py
jestit/helpers/dates.py
jestit/helpers/faker.py
jestit/helpers/logit.py
jestit/helpers/modules.py
jestit/helpers/paths.py
jestit/helpers/redis.py
jestit/helpers/request.py
jestit/helpers/settings.py
jestit/migrations/0001_initial.py
jestit/migrations/0002_jestitlog_method_alter_jestitlog_kind.py
jestit/migrations/__init__.py
jestit/models/__init__.py
jestit/models/base.py
jestit/models/logit.py
jestit/serializers/__init__.py
jestit/serializers/models.py
jestit/urls.py
metrics/README.md
metrics/__init__.py
metrics/redis_metrics.py
metrics/utils.py
renderit/__init__.py
taskit/README.md
taskit/__init__.py
taskit/manager.py
taskit/rest/__init__.py
taskit/rest/hooks.py
taskit/rest/tasks.py
taskit/runner.py
taskit/ti.py
testit/__init__.py
testit/client.py
testit/faker.py
testit/helpers.py
testit/runner.py
django_jestit-0.1.15.dist-info/LICENSE
django_jestit-0.1.15.dist-info/METADATA
django_jestit-0.1.15.dist-info/WHEEL
django_jestit-0.1.15.dist-info/RECORD
