Metadata-Version: 2.3
Name: django-jestit
Version: 0.1.15
Summary: 
License: MIT
Author: Ian Starnes
Author-email: ian@311labs.com
Requires-Python: >=3.8,<4.0
Classifier: License :: OSI Approved :: MIT License
Classifier: Programming Language :: Python :: 3
Classifier: Programming Language :: Python :: 3.8
Classifier: Programming Language :: Python :: 3.9
Classifier: Programming Language :: Python :: 3.10
Classifier: Programming Language :: Python :: 3.11
Classifier: Programming Language :: Python :: 3.12
Classifier: Programming Language :: Python :: 3.13
Requires-Dist: django (>=4.2.18,<6.0.0)
Requires-Dist: faker (>=35.2.0,<36.0.0)
Requires-Dist: pyjwt (>=2.10.1,<3.0.0)
Requires-Dist: pyobjict (>=2.0.0,<4.0.0)
Requires-Dist: redis (>=3.5.3,<6.0.0)
Requires-Dist: requests (>=2.32.3,<3.0.0)
Requires-Dist: ujson (>=5.10.0,<6.0.0)
